pyctem/__init__.py
pyctem/voltage.py
pyctem-0.0.1.dist-info/LICENSE
pyctem-0.0.1.dist-info/METADATA
pyctem-0.0.1.dist-info/WHEEL
pyctem-0.0.1.dist-info/top_level.txt
pyctem-0.0.1.dist-info/RECORD
