Metadata-Version: 2.1
Name: pyctem
Version: 0.0.1
Summary: A Python based toolset for computational S/TEM
Author-email: Tore Niermann <tore.niermann@tu-berlin.de>
License: Copyright (c) 2023, Tore Niermann
Project-URL: homepage, https://example.com
Classifier: Programming Language :: Python :: 3
Classifier: License :: OSI Approved :: BSD License
Classifier: Operating System :: OS Independent
Classifier: Development Status :: 2 - Pre-Alpha
Classifier: Intended Audience :: Science/Research
Classifier: Topic :: Scientific/Engineering
Requires-Python: >=3.7
License-File: LICENSE
Requires-Dist: scipy
